{
  "artifact_status": "non_final_gnss_baseline_exploration",
  "baselines": [
    {
      "assumption_summary": "Open-sky or otherwise usable GNSS access; no NTN cooperation needed.",
      "comparison_class": "external_service_reference",
      "continuous_gnss_required": true,
      "cooperation_required": false,
      "external_corrections_required": false,
      "fair_comparison_to_jcls": false,
      "gnss_required": true,
      "label": "standalone_gnss_reference",
      "oracle_diagnostic_reference": "reference",
      "safe_claim": "Useful as a familiar external PNT reference when GNSS is available.",
      "satellite_clock_correction_assumed": "GNSS broadcast orbit/clock correction and synchronized GNSS time.",
      "ue_clock_correction_assumed": "Receiver clock bias solved as part of the GNSS fix.",
      "unsafe_claim": "Do not claim it is an infrastructure-matched GNSS-denied baseline for JCLS."
    },
    {
      "assumption_summary": "Nominal, degraded 10 m, poor 100 m, and unavailable scenario levels.",
      "comparison_class": "scenario_stress_reference",
      "continuous_gnss_required": true,
      "cooperation_required": false,
      "external_corrections_required": false,
      "fair_comparison_to_jcls": false,
      "gnss_required": true,
      "label": "degraded_gnss_reference",
      "oracle_diagnostic_reference": "diagnostic_reference",
      "safe_claim": "Shows sensitivity to GNSS blockage or weak geometry as scenario assumptions.",
      "satellite_clock_correction_assumed": "Standard GNSS timing and broadcast corrections remain assumed.",
      "ue_clock_correction_assumed": "Receiver clock solved from degraded pseudorange geometry.",
      "unsafe_claim": "Do not present the 10 m or 100 m levels as literature values without a citation."
    },
    {
      "assumption_summary": "One-shot GNSS position prior with NTN/JCLS refinement after GNSS loss.",
      "comparison_class": "initialization_diagnostic",
      "continuous_gnss_required": false,
      "cooperation_required": true,
      "external_corrections_required": false,
      "fair_comparison_to_jcls": false,
      "gnss_required": true,
      "label": "gnss_aided_initialization",
      "oracle_diagnostic_reference": "diagnostic",
      "safe_claim": "Tests whether good external initialization removes the need for cooperative refinement.",
      "satellite_clock_correction_assumed": "Only the initial GNSS fix inherits GNSS satellite timing assumptions.",
      "ue_clock_correction_assumed": "Initial UE position prior is aided; clock aiding is not continuous.",
      "unsafe_claim": "Do not call this standalone JCLS because it injects external GNSS information."
    },
    {
      "assumption_summary": "Perfect clock, 1 ns, 10 ns, 100 ns, 1 us, and unconstrained cases.",
      "comparison_class": "clock_aided_diagnostic",
      "continuous_gnss_required": "variant-dependent",
      "cooperation_required": "variant-dependent",
      "external_corrections_required": false,
      "fair_comparison_to_jcls": false,
      "gnss_required": true,
      "label": "gnss_clock_aided_ntn",
      "oracle_diagnostic_reference": "oracle_for_perfect_clock_variant",
      "safe_claim": "Shows how much external clock synchronization changes NTN localization.",
      "satellite_clock_correction_assumed": "Known or tightly constrained satellite/network clocks.",
      "ue_clock_correction_assumed": "Known, tightly constrained, or periodically updated UE clocks.",
      "unsafe_claim": "Do not use the perfect-clock row as a fair synchronization baseline."
    },
    {
      "assumption_summary": "GNSS update intervals 1, 5, 15, and 30 s with ppm/ppb drift scenarios.",
      "comparison_class": "hybrid_outage_diagnostic",
      "continuous_gnss_required": false,
      "cooperation_required": "optional_hybrid",
      "external_corrections_required": false,
      "fair_comparison_to_jcls": false,
      "gnss_required": true,
      "label": "intermittent_gnss_update",
      "oracle_diagnostic_reference": "diagnostic",
      "safe_claim": "Quantifies holdover range bias between GNSS reacquisitions.",
      "satellite_clock_correction_assumed": "Clock is corrected only at GNSS update epochs.",
      "ue_clock_correction_assumed": "Clock uncertainty grows between updates according to oscillator drift.",
      "unsafe_claim": "Do not call the outage interval GNSS-free without accounting for prior GNSS information."
    },
    {
      "assumption_summary": "RTK, PPP, DGNSS, SBAS, or commercial correction-service infrastructure.",
      "comparison_class": "high_infrastructure_reference",
      "continuous_gnss_required": true,
      "cooperation_required": false,
      "external_corrections_required": true,
      "fair_comparison_to_jcls": false,
      "gnss_required": true,
      "label": "gnss_correction_service_reference",
      "oracle_diagnostic_reference": "reference",
      "safe_claim": "Provides high-performance GNSS context when corrections are available.",
      "satellite_clock_correction_assumed": "Precise orbit/clock corrections from an augmentation service.",
      "ue_clock_correction_assumed": "Receiver clock solved with augmented GNSS measurements.",
      "unsafe_claim": "Do not compare it as a fair GNSS-denied or infrastructure-matched JCLS baseline."
    },
    {
      "assumption_summary": "Signals, batching time, reference receiver, and orbit knowledge vary by paper.",
      "comparison_class": "literature_context_reference",
      "continuous_gnss_required": "literature-dependent",
      "cooperation_required": false,
      "external_corrections_required": "literature-dependent",
      "fair_comparison_to_jcls": false,
      "gnss_required": "literature-dependent",
      "label": "leo_pnt_literature_reference",
      "oracle_diagnostic_reference": "reference_only",
      "safe_claim": "Useful as context for LEO-PNT and Starlink signal-of-opportunity work.",
      "satellite_clock_correction_assumed": "Often assumes known or estimated LEO orbit/clock information.",
      "ue_clock_correction_assumed": "Estimated or externally aided depending on the paper.",
      "unsafe_claim": "Do not claim direct superiority or inferiority without reproducing the paper assumptions."
    }
  ],
  "bibliography_touched": false,
  "candidate_only": true,
  "existing_manuscript_result_files_touched": false,
  "generated_manuscript_pdfs_touched": false,
  "human_signoff_required": true,
  "manuscript_directories_touched": false,
  "manuscript_ready": false,
  "non_final": true,
  "not_for_manuscript_submission": true,
  "notebook_used": false,
  "psfrag_touched": false,
  "response_letter_touched": false,
  "work_in_progress_figures_touched": false
}